ugpy/__init__.py
ugpy/pw_utils/__init__.py
ugpy/pw_utils/cnn.py
ugpy/pw_utils/napari_utils.py
ugpy/pw_utils/synapse.py
ugpy/pw_utils/utils.py
ugpy/pw_visualize/__init__.py
ugpy/pw_visualize/viewers.py
ugpy/synspy/__init__.py
ugpy/synspy/register.py
ugpy/synspy/viewer.py
ugpy/synspy/viewer2d.py
ugpy/synspy/worker.py
ugpy/synspy/analyze/__init__.py
ugpy/synspy/analyze/block.py
ugpy/synspy/analyze/nexpr.py
ugpy/synspy/analyze/np.py
ugpy/synspy/analyze/ocl.py
ugpy/synspy/analyze/pair.py
ugpy/synspy/analyze/util.py
ugpy/temporary_stuff/__init__.py
ugpy/temporary_stuff/datasets.py
ugpy/temporary_stuff/loader.py
ugpy/temporary_stuff/models.py
ugpy/temporary_stuff/preprocess.py
ugpy/temporary_stuff/pw_core.py
ugpy/temporary_stuff/splitter.py
ugpy/temporary_stuff/train.py
ugpy/temporary_stuff/utils.py
ugpy-0.0.1.dist-info/LICENSE.md
ugpy-0.0.1.dist-info/METADATA
ugpy-0.0.1.dist-info/WHEEL
ugpy-0.0.1.dist-info/top_level.txt
ugpy-0.0.1.dist-info/RECORD
