Metadata-Version: 2.1
Name: ugpy
Version: 0.0.1
Summary: pythonic undergrad
Home-page: https://github.com/LemonJust/ugpy
Author: Anna Nadtochiy
Author-email: nadtochi@usc.edu
Classifier: Development Status :: 2 - Pre-Alpha
Classifier: Intended Audience :: Science/Research
Classifier: Topic :: Scientific/Engineering :: Image Processing
Classifier: Programming Language :: Python :: 3
Classifier: License :: OSI Approved :: MIT License
Classifier: Operating System :: OS Independent
Requires-Python: >=3.7
License-File: LICENSE.md
Requires-Dist: tifffile
Requires-Dist: numpy
Requires-Dist: tqdm
